[
  {
    "image": "/logos/individuals/CoryDoctorow.png",
    "name": "Cory Doctorow"
  },
  {
    "image": "/logos/individuals/EvangelineLilly.png",
    "name": "Evangeline Lilly"
  },
  {
    "image": "/logos/individuals/TomMorello.png",
    "name": "Tom Morello"
  },
  {
    "image": "/logos/individuals/JustinSun.png",
    "name": "Justin Sun"
  },
  {
    "image": "/logos/organizations/anchorfree.png",
    "name": "anchorfree"
  },
  {
    "image": "/logos/organizations/iFixit.png",
    "name": "iFixit"
  },
  {
    "image": "/logos/organizations/LookFar.png",
    "name": "LookFar"
  },
  {
    "image": "/logos/organizations/Namecheap.png",
    "name": "Namecheap"
  },
  {
    "image": "/logos/organizations/Pornhub.png",
    "name": "Pornhub"
  },
  {
    "image": "/logos/organizations/Postmates.png",
    "name": "Postmates"
  },
  {
    "image": "/logos/organizations/PrivateInternetAccess.png",
    "name": "Private Internet Access"
  },
  {
    "image": "/logos/organizations/StartPage.png",
    "name": "StartPage"
  },
  {
    "image": "/logos/organizations/Tron.png",
    "name": "Tron"
  }
]
